LICENSE.txt
MANIFEST.in
README.md
pyproject.toml
setup.cfg
setup.py
src/iri2016/CMakeLists.txt
src/iri2016/__init__.py
src/iri2016/altitude.py
src/iri2016/base.py
src/iri2016/build.py
src/iri2016/latitude.py
src/iri2016/plots.py
src/iri2016/profile.py
src/iri2016/setup.cmake
src/iri2016/time.py
src/iri2016.egg-info/PKG-INFO
src/iri2016.egg-info/SOURCES.txt
src/iri2016.egg-info/dependency_links.txt
src/iri2016.egg-info/not-zip-safe
src/iri2016.egg-info/requires.txt
src/iri2016.egg-info/top_level.txt
src/iri2016/data/ccir/ccir11.asc
src/iri2016/data/ccir/ccir12.asc
src/iri2016/data/ccir/ccir13.asc
src/iri2016/data/ccir/ccir14.asc
src/iri2016/data/ccir/ccir15.asc
src/iri2016/data/ccir/ccir16.asc
src/iri2016/data/ccir/ccir17.asc
src/iri2016/data/ccir/ccir18.asc
src/iri2016/data/ccir/ccir19.asc
src/iri2016/data/ccir/ccir20.asc
src/iri2016/data/ccir/ccir21.asc
src/iri2016/data/ccir/ccir22.asc
src/iri2016/data/igrf/dgrf1945.dat
src/iri2016/data/igrf/dgrf1950.dat
src/iri2016/data/igrf/dgrf1955.dat
src/iri2016/data/igrf/dgrf1960.dat
src/iri2016/data/igrf/dgrf1965.dat
src/iri2016/data/igrf/dgrf1970.dat
src/iri2016/data/igrf/dgrf1975.dat
src/iri2016/data/igrf/dgrf1980.dat
src/iri2016/data/igrf/dgrf1985.dat
src/iri2016/data/igrf/dgrf1990.dat
src/iri2016/data/igrf/dgrf1995.dat
src/iri2016/data/igrf/dgrf2000.dat
src/iri2016/data/igrf/dgrf2005.dat
src/iri2016/data/igrf/dgrf2010.dat
src/iri2016/data/igrf/dgrf2015.dat
src/iri2016/data/igrf/igrf2015.dat
src/iri2016/data/igrf/igrf2015s.dat
src/iri2016/data/igrf/igrf2020.dat
src/iri2016/data/index/apf107.dat
src/iri2016/data/index/ig_rz.dat
src/iri2016/data/mcsat/mcsat11.dat
src/iri2016/data/mcsat/mcsat12.dat
src/iri2016/data/mcsat/mcsat13.dat
src/iri2016/data/mcsat/mcsat14.dat
src/iri2016/data/mcsat/mcsat15.dat
src/iri2016/data/mcsat/mcsat16.dat
src/iri2016/data/mcsat/mcsat17.dat
src/iri2016/data/mcsat/mcsat18.dat
src/iri2016/data/mcsat/mcsat19.dat
src/iri2016/data/mcsat/mcsat20.dat
src/iri2016/data/mcsat/mcsat21.dat
src/iri2016/data/mcsat/mcsat22.dat
src/iri2016/data/ursi/ursi11.asc
src/iri2016/data/ursi/ursi12.asc
src/iri2016/data/ursi/ursi13.asc
src/iri2016/data/ursi/ursi14.asc
src/iri2016/data/ursi/ursi15.asc
