Metadata-Version: 2.1
Name: iri2016
Version: 1.11.1
Summary: IRI2016 International Reference Ionosphere from Python
Home-page: https://github.com/space-physics/iri2016
Author: Michael Hirsch, Ph.D.; Ronald Ilma
Author-email: scivision@users.noreply.github.com
License: UNKNOWN
Keywords: thermosphere,ionosphere
Platform: UNKNOWN
Classifier: Development Status :: 5 - Production/Stable
Classifier: Environment :: Console
Classifier: Intended Audience :: Science/Research
Classifier: Operating System :: OS Independent
Classifier: Programming Language :: Fortran
Classifier: Programming Language :: Python :: 3
Classifier: Topic :: Scientific/Engineering :: Atmospheric Science
Requires-Python: >=3.7
Provides-Extra: tests
Provides-Extra: lint
Provides-Extra: plot
